open_web_calendar/__init__.py
open_web_calendar/__main__.py
open_web_calendar/_version.py
open_web_calendar/app.py
open_web_calendar/clean_html.py
open_web_calendar/config.py
open_web_calendar/default_specification.yml
open_web_calendar/encryption.py
open_web_calendar/error.py
open_web_calendar/new_key.py
open_web_calendar/translate.py
open_web_calendar/url.py
open_web_calendar/util.py
open_web_calendar/version.py
open_web_calendar/calendars/__init__.py
open_web_calendar/calendars/base.py
open_web_calendar/calendars/caldav.py
open_web_calendar/calendars/errors.py
open_web_calendar/calendars/ics.py
open_web_calendar/calendars/info/__init__.py
open_web_calendar/calendars/info/dict.py
open_web_calendar/calendars/info/ics.py
open_web_calendar/calendars/info/interface.py
open_web_calendar/calendars/info/list.py
open_web_calendar/calendars/info/url.py
open_web_calendar/convert/__init__.py
open_web_calendar/convert/base.py
open_web_calendar/convert/calendar.py
open_web_calendar/convert/events.py
open_web_calendar/convert/ics.py
open_web_calendar/static/css/about.css
open_web_calendar/static/css/common.css
open_web_calendar/static/css/index.css
open_web_calendar/static/css/dhtmlx/README.md
open_web_calendar/static/css/dhtmlx/dhtmlxscheduler.css
open_web_calendar/static/css/dhtmlx/dhtmlxscheduler.css.license
open_web_calendar/static/css/dhtmlx/style.css
open_web_calendar/static/css/dhtmlx/dhtmlxscheduler_material/fonts.googleapis.com/KFOlCnqEu92Fr1MmEU9fABc4EsA.woff2
open_web_calendar/static/css/dhtmlx/dhtmlxscheduler_material/fonts.googleapis.com/KFOlCnqEu92Fr1MmEU9fBBc4.woff2
open_web_calendar/static/css/dhtmlx/dhtmlxscheduler_material/fonts.googleapis.com/KFOlCnqEu92Fr1MmEU9fBxc4EsA.woff2
open_web_calendar/static/css/dhtmlx/dhtmlxscheduler_material/fonts.googleapis.com/KFOlCnqEu92Fr1MmEU9fCBc4EsA.woff2
open_web_calendar/static/css/dhtmlx/dhtmlxscheduler_material/fonts.googleapis.com/KFOlCnqEu92Fr1MmEU9fCRc4EsA.woff2
open_web_calendar-1.51.dist-info/METADATA
open_web_calendar-1.51.dist-info/WHEEL
open_web_calendar-1.51.dist-info/entry_points.txt
open_web_calendar-1.51.dist-info/licenses/LICENSE
open_web_calendar-1.51.dist-info/RECORD
