Metadata-Version: 2.4
Name: open-web-calendar
Version: 1.51
Summary: Embed a highly customizable web calendar into your website using ICal source links
Project-URL: Homepage, https://open-web-calendar.hosted.quelltext.eu/
Project-URL: Repository, https://github.com/niccokunzmann/open-web-calendar/
Project-URL: source_archive, https://github.com/niccokunzmann/open-web-calendar/archive/d6e46c66be4e5aea5b6ffe922f5629eecf086fd2.zip
Project-URL: Issues, https://github.com/niccokunzmann/open-web-calendar/issues
Project-URL: Documentation, https://open-web-calendar.quelltext.eu/
Project-URL: Changelog, https://open-web-calendar.quelltext.eu/changelog/
Author: Open Web Calendar Contributors
Author-email: Nicco Kunzmann <niccokunzmann@rambler.ru>
Maintainer-email: Nicco Kunzmann <niccokunzmann@rambler.ru>
License:                     GNU GENERAL PUBLIC LICENSE
License-File: LICENSE
Keywords: HTML,OpenWebCalendar,calendar,embed,icalendar,ics,iframe,rfc5545,scheduling,website
Classifier: Development Status :: 5 - Production/Stable
Classifier: Framework :: Flask
Classifier: Intended Audience :: Developers
Classifier: License :: OSI Approved :: GNU General Public License v2 (GPLv2)
Classifier: Natural Language :: Chinese (Simplified)
Classifier: Natural Language :: Croatian
Classifier: Natural Language :: English
Classifier: Natural Language :: Esperanto
Classifier: Natural Language :: French
Classifier: Natural Language :: German
Classifier: Natural Language :: Indonesian
Classifier: Natural Language :: Italian
Classifier: Natural Language :: Norwegian
Classifier: Natural Language :: Polish
Classifier: Natural Language :: Spanish
Classifier: Natural Language :: Turkish
Classifier: Operating System :: OS Independent
Classifier: Programming Language :: Python :: 3
Classifier: Topic :: Internet :: WWW/HTTP :: HTTP Servers
Classifier: Topic :: Office/Business :: Scheduling
Requires-Python: >=3.9
Requires-Dist: bcrypt
Requires-Dist: beautifulsoup4
Requires-Dist: caldav
Requires-Dist: cryptography
Requires-Dist: flask
Requires-Dist: flask-allowed-hosts
Requires-Dist: gunicorn
Requires-Dist: icalendar-compatibility>=0.1.3
Requires-Dist: icalendar>=6.3.0
Requires-Dist: lxml
Requires-Dist: lxml-html-clean
Requires-Dist: mergecal>=0.4.2
Requires-Dist: pyyaml
Requires-Dist: recurring-ical-events>=3.7.0
Requires-Dist: requests
Requires-Dist: requests-cache>=1.3.0a0
Requires-Dist: requests[socks]
Provides-Extra: dev
Requires-Dist: pip-compile-multi; extra == 'dev'
Requires-Dist: tox; extra == 'dev'
Provides-Extra: dev-fix
Requires-Dist: build==1.3.0; extra == 'dev-fix'
Requires-Dist: cachetools==6.1.0; extra == 'dev-fix'
Requires-Dist: chardet==5.2.0; extra == 'dev-fix'
Requires-Dist: click==8.2.0; extra == 'dev-fix'
Requires-Dist: colorama==0.4.6; extra == 'dev-fix'
Requires-Dist: distlib==0.4.0; extra == 'dev-fix'
Requires-Dist: filelock==3.19.1; extra == 'dev-fix'
Requires-Dist: packaging==25.0; extra == 'dev-fix'
Requires-Dist: pip-compile-multi==3.2.1; extra == 'dev-fix'
Requires-Dist: pip-tools==7.5.0; extra == 'dev-fix'
Requires-Dist: platformdirs==4.3.8; extra == 'dev-fix'
Requires-Dist: pluggy==1.6.0; extra == 'dev-fix'
Requires-Dist: pyproject-api==1.9.1; extra == 'dev-fix'
Requires-Dist: pyproject-hooks==1.2.0; extra == 'dev-fix'
Requires-Dist: toposort==1.10; extra == 'dev-fix'
Requires-Dist: tox==4.28.4; extra == 'dev-fix'
Requires-Dist: virtualenv==20.34.0; extra == 'dev-fix'
Requires-Dist: wheel==0.45.1; extra == 'dev-fix'
Provides-Extra: production
Requires-Dist: attrs==25.3.0; extra == 'production'
Requires-Dist: bcrypt==4.3.0; extra == 'production'
Requires-Dist: beautifulsoup4==4.13.4; extra == 'production'
Requires-Dist: blinker==1.9.0; extra == 'production'
Requires-Dist: caldav==1.5.0; extra == 'production'
Requires-Dist: cattrs==25.1.1; extra == 'production'
Requires-Dist: certifi==2025.8.3; extra == 'production'
Requires-Dist: cffi==1.17.1; extra == 'production'
Requires-Dist: charset-normalizer==3.4.3; extra == 'production'
Requires-Dist: click==8.1.8; extra == 'production'
Requires-Dist: cryptography==45.0.6; extra == 'production'
Requires-Dist: flask-allowed-hosts==1.2.0; extra == 'production'
Requires-Dist: flask==3.1.1; extra == 'production'
Requires-Dist: gunicorn==23.0.0; extra == 'production'
Requires-Dist: icalendar-compatibility==0.1.4; extra == 'production'
Requires-Dist: icalendar==6.3.1; extra == 'production'
Requires-Dist: idna==3.10; extra == 'production'
Requires-Dist: itsdangerous==2.2.0; extra == 'production'
Requires-Dist: jinja2==3.1.6; extra == 'production'
Requires-Dist: lxml-html-clean==0.4.2; extra == 'production'
Requires-Dist: lxml==6.0.0; extra == 'production'
Requires-Dist: markdown-it-py==3.0.0; extra == 'production'
Requires-Dist: markupsafe==3.0.2; extra == 'production'
Requires-Dist: mdurl==0.1.2; extra == 'production'
Requires-Dist: mergecal==0.5.0; extra == 'production'
Requires-Dist: packaging==25.0; extra == 'production'
Requires-Dist: platformdirs==4.3.8; extra == 'production'
Requires-Dist: pycparser==2.22; extra == 'production'
Requires-Dist: pygments==2.19.2; extra == 'production'
Requires-Dist: pysocks==1.7.1; extra == 'production'
Requires-Dist: python-dateutil==2.9.0.post0; extra == 'production'
Requires-Dist: pytz==2025.2; extra == 'production'
Requires-Dist: pyyaml==6.0.2; extra == 'production'
Requires-Dist: recurring-ical-events==3.8.0; extra == 'production'
Requires-Dist: requests-cache==1.3.0a0; extra == 'production'
Requires-Dist: requests[socks]==2.32.4; extra == 'production'
Requires-Dist: rich==14.1.0; extra == 'production'
Requires-Dist: shellingham==1.5.4; extra == 'production'
Requires-Dist: six==1.17.0; extra == 'production'
Requires-Dist: soupsieve==2.7; extra == 'production'
Requires-Dist: typer==0.16.0; extra == 'production'
Requires-Dist: typing-extensions==4.13.2; extra == 'production'
Requires-Dist: tzdata==2025.2; extra == 'production'
Requires-Dist: url-normalize==2.2.1; extra == 'production'
Requires-Dist: urllib3==2.4.0; extra == 'production'
Requires-Dist: vobject==0.9.9; extra == 'production'
Requires-Dist: werkzeug==3.1.3; extra == 'production'
Requires-Dist: x-wr-timezone==2.0.1; extra == 'production'
Provides-Extra: test
Requires-Dist: behave; extra == 'test'
Requires-Dist: pytest; extra == 'test'
Requires-Dist: pytest-responses; extra == 'test'
Requires-Dist: responses; extra == 'test'
Requires-Dist: reuse; extra == 'test'
Requires-Dist: ruff; extra == 'test'
Requires-Dist: selenium; extra == 'test'
Provides-Extra: test-fix
Requires-Dist: attrs==25.3.0; extra == 'test-fix'
Requires-Dist: behave==1.3.1; extra == 'test-fix'
Requires-Dist: binaryornot==0.4.4; extra == 'test-fix'
Requires-Dist: boolean-py==5.0; extra == 'test-fix'
Requires-Dist: certifi==2025.8.3; extra == 'test-fix'
Requires-Dist: chardet==5.2.0; extra == 'test-fix'
Requires-Dist: charset-normalizer==3.4.3; extra == 'test-fix'
Requires-Dist: click==8.1.8; extra == 'test-fix'
Requires-Dist: h11==0.16.0; extra == 'test-fix'
Requires-Dist: idna==3.10; extra == 'test-fix'
Requires-Dist: iniconfig==2.1.0; extra == 'test-fix'
Requires-Dist: jinja2==3.1.6; extra == 'test-fix'
Requires-Dist: license-expression==30.4.4; extra == 'test-fix'
Requires-Dist: markupsafe==3.0.2; extra == 'test-fix'
Requires-Dist: outcome==1.3.0.post0; extra == 'test-fix'
Requires-Dist: packaging==25.0; extra == 'test-fix'
Requires-Dist: parse-type==0.6.6; extra == 'test-fix'
Requires-Dist: parse==1.20.2; extra == 'test-fix'
Requires-Dist: pluggy==1.6.0; extra == 'test-fix'
Requires-Dist: pysocks==1.7.1; extra == 'test-fix'
Requires-Dist: pytest-responses==0.5.1; extra == 'test-fix'
Requires-Dist: pytest==8.4.1; extra == 'test-fix'
Requires-Dist: python-debian==1.0.1; extra == 'test-fix'
Requires-Dist: pyyaml==6.0.2; extra == 'test-fix'
Requires-Dist: requests==2.32.4; extra == 'test-fix'
Requires-Dist: responses==0.25.8; extra == 'test-fix'
Requires-Dist: reuse==5.0.2; extra == 'test-fix'
Requires-Dist: ruff==0.12.9; extra == 'test-fix'
Requires-Dist: selenium==4.33.0; extra == 'test-fix'
Requires-Dist: six==1.17.0; extra == 'test-fix'
Requires-Dist: sniffio==1.3.1; extra == 'test-fix'
Requires-Dist: sortedcontainers==2.4.0; extra == 'test-fix'
Requires-Dist: tomlkit==0.13.3; extra == 'test-fix'
Requires-Dist: trio-websocket==0.12.2; extra == 'test-fix'
Requires-Dist: trio==0.30.0; extra == 'test-fix'
Requires-Dist: typing-extensions==4.13.2; extra == 'test-fix'
Requires-Dist: urllib3[socks]==2.4.0; extra == 'test-fix'
Requires-Dist: websocket-client==1.8.0; extra == 'test-fix'
Requires-Dist: wsproto==1.2.0; extra == 'test-fix'
